pynumcalc/__init__.py
pynumcalc/_diffquot.py
pynumcalc/_finitediff.py
pynumcalc/_riemannsum.py
pynumcalc/_typedef.py
pynumcalc/integral.py
pynumcalc/tests/__init__.py
pynumcalc/tests/test_integral.py
pynumcalc-0.2.1.dist-info/LICENSE
pynumcalc-0.2.1.dist-info/METADATA
pynumcalc-0.2.1.dist-info/WHEEL
pynumcalc-0.2.1.dist-info/top_level.txt
pynumcalc-0.2.1.dist-info/RECORD
