Metadata-Version: 2.1
Name: pynumcalc
Version: 0.2.1
Summary: A Python package for numerical differential and integral calculus approximations.
Author-email: Jacob Lee <Jacob.J.Lee@outlook.com>
License: MIT License
Project-URL: homepage, https://github.com/JacobLee23/pynumcalc
Classifier: Development Status :: 2 - Pre-Alpha
Classifier: License :: OSI Approved :: MIT License
Classifier: Natural Language :: English
Classifier: Operating System :: OS Independent
Classifier: Programming Language :: Python
Classifier: Programming Language :: Python :: 3
Classifier: Programming Language :: Python :: 3.8
Classifier: Programming Language :: Python :: 3.9
Classifier: Programming Language :: Python :: 3.10
Classifier: Programming Language :: Python :: 3.11
Classifier: Programming Language :: Python :: 3.12
Requires-Python: >=3.8
License-File: LICENSE
Requires-Dist: numpy ==1.26.2 ; python_version >= "3.9"
Requires-Dist: scipy ==1.11.4 ; python_version >= "3.9"
